django_environment_settings.py
django_environment_settings-0.1.2.dist-info/LICENSE
django_environment_settings-0.1.2.dist-info/METADATA
django_environment_settings-0.1.2.dist-info/WHEEL
django_environment_settings-0.1.2.dist-info/top_level.txt
django_environment_settings-0.1.2.dist-info/RECORD
