Metadata-Version: 2.1
Name: django-environment-settings
Version: 0.1.2
Summary: 允许Django应用从settings.py或环境变量中获取配置。
Author: rRR0VrFP
Maintainer: rRR0VrFP
License: Apache License, Version 2.0
Keywords: django,settings,environment
Classifier: Development Status :: 5 - Production/Stable
Classifier: Intended Audience :: Developers
Classifier: Topic :: Software Development :: Libraries :: Python Modules
Classifier: License :: OSI Approved :: Apache Software License
Classifier: Programming Language :: Python :: 3
Classifier: Programming Language :: Python :: 3 :: Only
License-File: LICENSE
Requires-Dist: python-environment-settings
